pricing/__init__.py
pricing/babel_numbers.py
pricing/exceptions.py
pricing/exchange.py
pricing/fields.py
pricing/formats.py
pricing/interfaces.py
pricing/metaconfigure.py
pricing/metadirectives.py
pricing/price.py
pricing/range.py
pricing/uris.py
pricing-1.0.1.dist-info/METADATA
pricing-1.0.1.dist-info/RECORD
pricing-1.0.1.dist-info/WHEEL
pricing-1.0.1.dist-info/top_level.txt
tests/__init__.py
tests/mixins.py
tests/test_babel_numbers.py
tests/test_coinbase_backend.py
tests/test_directives.py
tests/test_docs.py
tests/test_exchange.py
tests/test_fields.py
tests/test_formats.py
tests/test_price.py
tests/test_range.py
tests/test_uris.py
tests/test_xprice.py
