Metadata-Version: 2.1
Name: pricing
Version: 1.0.1
Summary: Python Pricing Package
Home-page: https://github.com/joeblackwaslike/pricing
Author: Joe Black
Author-email: me@joeblack.nyc
Maintainer: Joe Black
Maintainer-email: me@joeblack.nyc
License: MIT
Download-URL: https://github.com/joeblackwaslike/pricing/tarball/v1.0.1
Keywords: money,price,pricing,currency,cryptocurrency,bitcoin,exchange,rates,ranges,formats
Platform: UNKNOWN
Classifier: Development Status :: 4 - Beta
Classifier: Intended Audience :: Developers
Classifier: Operating System :: OS Independent
Classifier: Natural Language :: English
Classifier: License :: OSI Approved :: MIT License
Classifier: Programming Language :: Python :: 3.5
Classifier: Programming Language :: Python :: 3.6
Classifier: Programming Language :: Python :: 3.7
Classifier: Programming Language :: Python :: 3 :: Only
Classifier: Topic :: Internet :: WWW/HTTP
Classifier: Topic :: Software Development
Classifier: Topic :: Utilities
Classifier: Topic :: Software Development :: Libraries :: Python Modules
Classifier: Topic :: Software Development :: Libraries
Requires-Dist: zope.interface (>=4.5.0)
Requires-Dist: zope.configuration (>=4.1.0)
Requires-Dist: zope.component (>=4.4.1)
Requires-Dist: requests (>=2.18.4)
Requires-Dist: zulu (>=0.12.0)
Requires-Dist: attrs (>=18.1.0)
Requires-Dist: babel (>=2.5.3)
Requires-Dist: boltons (>=18.0.0)
